MANIFEST.in
README.txt
setup.cfg
setup.py
c2/__init__.py
c2.transform.msoffice.egg-info/PKG-INFO
c2.transform.msoffice.egg-info/SOURCES.txt
c2.transform.msoffice.egg-info/dependency_links.txt
c2.transform.msoffice.egg-info/entry_points.txt
c2.transform.msoffice.egg-info/namespace_packages.txt
c2.transform.msoffice.egg-info/not-zip-safe
c2.transform.msoffice.egg-info/requires.txt
c2.transform.msoffice.egg-info/top_level.txt
c2/transform/.DS_Store
c2/transform/__init__.py
c2/transform/msoffice/.DS_Store
c2/transform/msoffice/__init__.py
c2/transform/msoffice/config.py
c2/transform/msoffice/configure.zcml
c2/transform/msoffice/msdoc2txt.jar
c2/transform/msoffice/setuphandlers.py
c2/transform/msoffice/transform.py
c2/transform/msoffice/version.txt
c2/transform/msoffice/javasrc/README.md
c2/transform/msoffice/profiles/default/import_steps.xml
c2/transform/msoffice/profiles/default/metadata.xml
c2/transform/msoffice/tests/__init__.py
c2/transform/msoffice/tests/test_main.py
c2/transform/msoffice/tests/wordprocessing1.docx
docs/HISTORY.txt
docs/INSTALL.txt
docs/LICENSE.GPL
docs/LICENSE.txt