Metadata-Version: 1.1
Name: c2.transform.msoffice
Version: 1.0b6
Summary: This product enables to search MS-Office files on Plone.
Home-page: http://www.cmscom.jp
Author: Manabu Terada
Author-email: terada@cmscom.jp
License: GPL
Keywords: Plone transform MS Office search
Platform: UNKNOWN
Classifier: Framework :: Plone
Classifier: Programming Language :: Python
Classifier: Topic :: Software Development :: Libraries :: Python Modules
